grpc_utils/__init__.py
grpc_utils/server.py
grpc_utils-1.0.0.dist-info/METADATA
grpc_utils-1.0.0.dist-info/RECORD
grpc_utils-1.0.0.dist-info/WHEEL
grpc_utils-1.0.0.dist-info/top_level.txt
