Metadata-Version: 2.1
Name: grpc-utils
Version: 1.0.0
Summary: Utils for working with gRPC in Python
Home-page: https://github.com/AlekzanderDee/grpc-utils
Author: Alexander Dultsev
License: MIT
Keywords: grpc development
Platform: UNKNOWN
Classifier: Development Status :: 4 - Beta
Classifier: Intended Audience :: Developers
Classifier: Topic :: Software Development :: Build Tools
Classifier: License :: OSI Approved :: MIT License
Classifier: Programming Language :: Python :: 3.5
Classifier: Programming Language :: Python :: 3.6
Requires-Dist: grpcio (>=1.22.0)
